feasytools/__init__.py
feasytools/argchk.py
feasytools/geo.py
feasytools/i18n.py
feasytools/pdf.py
feasytools/perf.py
feasytools/pq.py
feasytools/rangelist.py
feasytools/table.py
feasytools/tfunc.py
feasytools/ufs.py
feasytools-0.1.4.dist-info/METADATA
feasytools-0.1.4.dist-info/WHEEL
feasytools-0.1.4.dist-info/licenses/LICENSE
feasytools-0.1.4.dist-info/RECORD
