Metadata-Version: 2.4
Name: feasytools
Version: 0.1.4
Summary: A package of some useful tools
Author: fmy-xfk
License-Expression: MIT
License-File: LICENSE
Classifier: License :: OSI Approved :: MIT License
Classifier: Operating System :: OS Independent
Classifier: Programming Language :: Python :: 3
Requires-Python: >=3.6
